pquiz/__init__.py
pquiz/__main__.py
pquiz/pquiz.py
pquiz-1.0.dist-info/LICENSE
pquiz-1.0.dist-info/WHEEL
pquiz-1.0.dist-info/METADATA
pquiz-1.0.dist-info/RECORD
