Metadata-Version: 2.1
Name: pquiz
Version: 1.0
Summary: Ports quiz
Author-email: Caronte Gianluca <dev@caronte.me>
Classifier: License :: OSI Approved :: MIT License
Requires-Dist: termcolor >=1.1.0
Project-URL: Home, https://github.com/Janluke0/pquiz
